CHANGES.txt
LICENSE.txt
MANIFEST.in
README.rst
setup.py
docs/Makefile
docs/make.bat
docs/source/conf.py
docs/source/index.rst
trait_documenter/__init__.py
trait_documenter/_version.py
trait_documenter/class_trait_documenter.py
trait_documenter/module_trait_documenter.py
trait_documenter/util.py
trait_documenter.egg-info/PKG-INFO
trait_documenter.egg-info/SOURCES.txt
trait_documenter.egg-info/dependency_links.txt
trait_documenter.egg-info/requires.txt
trait_documenter.egg-info/top_level.txt
trait_documenter/tests/__init__.py
trait_documenter/tests/test_class_trait_documenter.py
trait_documenter/tests/test_file.py
trait_documenter/tests/test_file2.py
trait_documenter/tests/test_get_trait_definition.py
trait_documenter/tests/test_module_trait_documenter.py
trait_documenter/tests/test_sphinx_setup.py
trait_documenter/tests/testing.py