Metadata-Version: 1.1
Name: trait-documenter
Version: 1.1.0
Summary: Autodoc extention for documenting traits
Home-page: https://github.com/enthought/trait-documenter
Author: Ioannis Tziakos
Author-email: info@enthought.com
License: BSD
Platform: UNKNOWN
Classifier: Programming Language :: Python :: 2.6
Classifier: Programming Language :: Python :: 2.7
Classifier: Programming Language :: Python :: 3.2
Classifier: Programming Language :: Python :: 3.3
Classifier: Programming Language :: Python :: 3.4
Classifier: Programming Language :: Python :: 3.5
Classifier: Development Status :: 5 - Production/Stable
Classifier: Intended Audience :: Developers
Classifier: License :: OSI Approved :: BSD License
Classifier: Operating System :: OS Independent
Classifier: Programming Language :: Python
Classifier: Framework :: Sphinx :: Extension
Classifier: Topic :: Documentation :: Sphinx
